stockdatautils/__init__.py
stockdatautils/ingest/__init__.py
stockdatautils/ingest/ingestion_utils.py
stockdatautils/ingest/metadata_utils.py
stockdatautils/ingest/utils.py
stockdatautils-0.1.6.dist-info/METADATA
stockdatautils-0.1.6.dist-info/WHEEL
stockdatautils-0.1.6.dist-info/RECORD
