Metadata-Version: 2.1
Name: stockdatautils
Version: 0.1.6
Summary: 
Author: Tomos Corbin
Author-email: tom_corbin1@hotmail.com
Requires-Python: >=3.12,<4.0
Classifier: Programming Language :: Python :: 3
Classifier: Programming Language :: Python :: 3.12
Requires-Dist: pymongo (>=4.8.0,<5.0.0)
Requires-Dist: requests (>=2.32.3,<3.0.0)
Requires-Dist: yfinance (>=0.2.40,<0.3.0)
